{
    "name": "imagecloud",
    "title": "imageCloud",
    "description": "jQuery plug-in based on Google's Doodle designed for the Christmas holidays on 2010.",
    "keywords": [
        "image",
		"gallery",
        "animation",
		"slideshow",
		"jquery",
		"photo",
		"cloud",
		"doodle",
		"google"
    ],
    "version": "3.1.0",
    "author": {
        "name": "Alvaro Montoro",
		"email": "alvaromontoro@gmail.com",
        "url": "http://www.alvaromontoro.com"
    },
    "licenses": [
        {
            "type": "GPLv3",
			"url": "http://opensource.org/licenses/GPL-3.0"
        }
    ],
    "bugs": "https://github.com/alvaromontoro/ImageCloud/issues",
    "homepage": "https://github.com/alvaromontoro/ImageCloud",
    "docs": "https://github.com/alvaromontoro/ImageCloud/wiki",
    "download": "https://github.com/alvaromontoro/ImageCloud/releases",
	"demo":"http://alvaromontoro.com/jquery/imageCloud/demo.php",
    "dependencies": {
        "jquery": ">=1.5"
    }
}
